license_checker/__init__.py
license_checker/cli.py
license_checker/license_meta.py
license_checker/scanner.py
license_checker-0.1.3.dist-info/METADATA
license_checker-0.1.3.dist-info/WHEEL
license_checker-0.1.3.dist-info/entry_points.txt
license_checker-0.1.3.dist-info/top_level.txt
license_checker-0.1.3.dist-info/RECORD
