Metadata-Version: 2.4
Name: license_checker
Version: 0.1.3
Summary: Scan Python sources for imports and check distribution licenses.
Author: Student
License-Expression: MIT
Project-URL: Homepage, https://example.com/import-license-checker
Keywords: license,compliance,imports,security,supply-chain
Classifier: Programming Language :: Python :: 3
Classifier: Topic :: Software Development :: Build Tools
Classifier: Topic :: Security
Requires-Python: >=3.8
Requires-Dist: requests
